__init__.py
dmponline.py
question_overview.py
dmponline-0.0.1.dist-info/LICENSE
dmponline-0.0.1.dist-info/METADATA
dmponline-0.0.1.dist-info/WHEEL
dmponline-0.0.1.dist-info/entry_points.txt
dmponline-0.0.1.dist-info/top_level.txt
dmponline-0.0.1.dist-info/RECORD
