Metadata-Version: 2.1
Name: dmponline
Version: 0.0.1
Summary: Python interface to DMPonline API
Author: Kees den Heijer
Author-email: c.denheijer@tudelft.nl
Classifier: Programming Language :: Python :: 3
Classifier: License :: OSI Approved :: MIT License
Classifier: Operating System :: OS Independent
Requires-Python: >=3.6
License-File: LICENSE
Requires-Dist: pandas (>=1.5)
Requires-Dist: requests (>=2.28.1)
